authspnego/__init__.py
authspnego/middleware.py
django_auth_spnego-0.1.1.dist-info/DESCRIPTION.rst
django_auth_spnego-0.1.1.dist-info/METADATA
django_auth_spnego-0.1.1.dist-info/metadata.json
django_auth_spnego-0.1.1.dist-info/RECORD
django_auth_spnego-0.1.1.dist-info/top_level.txt
django_auth_spnego-0.1.1.dist-info/WHEEL
