Metadata-Version: 2.0
Name: django-auth-spnego
Version: 0.1.1
Summary: SPNEGO Kerberos authentication middleware for django
Home-page: https://github.com/AzMoo/django-auth-spnego
Author: Matt Magin
Author-email: matt.azmoo@gmail.com
License: MIT
Keywords: django spnego auth ldap middleware
Platform: UNKNOWN
Classifier: Development Status :: 3 - Alpha
Classifier: Environment :: Web Environment
Classifier: Framework :: Django :: 1.11
Classifier: Framework :: Django :: 1.10
Classifier: License :: OSI Approved :: MIT License
Classifier: Natural Language :: English
Classifier: Programming Language :: Python :: 3.3
Classifier: Programming Language :: Python :: 3.4
Classifier: Programming Language :: Python :: 3.5
Classifier: Programming Language :: Python :: 3.6
Classifier: Programming Language :: Python :: 3 :: Only
Classifier: Topic :: Internet :: WWW/HTTP :: WSGI :: Middleware
Classifier: Topic :: System :: Systems Administration :: Authentication/Directory :: LDAP
Requires-Python: >=3.4
Requires-Dist: django
Requires-Dist: kerberos
Requires-Dist: django-auth-ldap
